ptysh_base.py
ptysh_main.py
ptysh_module.py
ptysh_util.py
setup.py
daemon_example/__init__.py
daemon_example/test_daemon.py
modules/__init__.py
modules/test_module.py
ptysh.egg-info/PKG-INFO
ptysh.egg-info/SOURCES.txt
ptysh.egg-info/dependency_links.txt
ptysh.egg-info/requires.txt
ptysh.egg-info/top_level.txt