Metadata-Version: 1.1
Name: ptysh
Version: 0.1.0
Summary: Python Teletype Shell
Home-page: https://github.com/IPOT/PTYSH
Author: kssim
Author-email: ksub0912@gmail.com
License: MIT License
Keywords: shell,tty,terminal
Platform: UNKNOWN
Classifier: Development Status :: 3 - Alpha
Classifier: Intended Audience :: Developers
Classifier: License :: OSI Approved :: MIT License
Classifier: Programming Language :: Python
Classifier: Programming Language :: Python :: 2
Classifier: Programming Language :: Python :: 3
Classifier: Operating System :: POSIX :: Linux
Classifier: Topic :: Software Development
Classifier: Topic :: System :: Installation/Setup
Classifier: Topic :: System :: System Shells
Classifier: Topic :: System :: Shells
Classifier: Topic :: Terminals
Classifier: Topic :: Utilities
